{
  "ComponentName": "MLS-2 Launcher",
  "LongDescription": "The MLS-2 is a roll-off missile launcher, loaded by crew members who retrieve munitions from bulk magazines. The MLS-2 can fire a volley of 4 medium-size missiles, like the SGM-series, before requiring a reload. As the reloading process is complicated, the MLS is restricted to firing currently loaded missiles, while swapping missiles requires a complete reload.",
  "FlavorText": "The design is timeless, the engineering efficient, and the shape immediately recognizable. A textbook example of Alliance pragmatism, you don't need a fancy hydraulic door, just some missiles on racks and a slot that opens up to the vacuum.\n\nStill doesn't make reloading it any easier, though. Payloads have to be hooked up to a specialized controller that feeds targeting data to the missiles and that's not counting the physical strength needed to combat swap loaded missiles. That's mostly why you see VLS in place of these but that wouldn't exactly do the \"massed fire\" doctrine any justice, now would it?\n\n- T. Meadows, LT",
  "Category": "Weapons - Missile",
  "Type": "Surface",
  "CompoundingCost": false,
  "CompoundingMultiplier": 1,
  "CompoundingCostClass": "MLS-2 Launcher",
  "FirstInstanceFree": false,
  "PointCost": 20,
  "Mass": 7.5,
  "Size": {
    "x": 2,
    "y": 2,
    "z": 3
  },
  "CanTile": false,
  "MaxHealth": 100,
  "Reinforced": false,
  "FunctioningThreshold": 10,
  "DamageResistance": 15,
  "DCPriority": "Medium",
  "RareDebuffSubtype": "",
  "RareDebuffChance": 0.05,
  "FormattedResources": "Power: <color=#FF2525>-50 kW</color>\n",
  "ResourceDemandPriority": "High",
  "FormattedBuffs": "",
  "IWeaponData": {
    "WepType": "Missile",
    "OptimalTargetWeight": "Heavy",
    "PDTTargetMethod": "Direct",
    "NeedsExternalAmmoFeed": true,
    "SupportsAmmoSelection": true,
    "SupportsPositionTargeting": false,
    "PositionTargetingNoInput": false,
    "SupportsTrackTargeting": false,
    "SupportsVisualTargeting": false,
    "SupportsTargetReferencePoints": false
  },
  "WeaponComponentData": null,
  "ContinuousWeaponComponentData": null,
  "DiscreteWeaponComponentData": null,
  "CellLauncherComponentData": null,
  "TubeLauncherComponentData": {
    "TimeBetweenLaunches": 0.5,
    "MissileSize": 2,
    "LaunchesPerLoad": 4,
    "LoadTime": 45
  },
  "FixedContinuousWeaponComponentData": null,
  "MuzzleData": null,
  "RaycastDamageCharacteristicData": null,
  "RaycastDamageFalloffData": null,
  "CommsAntennaComponentData": null,
  "OmnidirectionalEWarComponentData": null,
  "TurretedEWarComponentData": null,
  "ISensorComponentData": null,
  "PassiveSensorComponentData": null,
  "SensorComponentData": null,
  "FireControlData": null,
  "IEWarTargetData": null,
  "SensorTurretComponentData": null,
  "TurretedContinuousWeaponComponentData": null,
  "TurretedDiscreteWeaponComponentData": null,
  "IIntelComponentData": null,
  "CommandComponentData": null,
  "IntelligenceComponentData": null,
  "BerthingComponentData": null,
  "CrewOperatedComponentData": {
    "CrewRequired": 10,
    "ReinforceCrewAt": -1
  },
  "DCLockerComponentData": null,
  "IMagazineProviderData": null,
  "BulkMagazineComponentData": null
}