{
  "key": "CIS/Providence",
  "name": "'Providence' class Destroyer",
  "mounts": {
    "mount868_1": "8x6x8",
    "mount868_2": "8x6x8",
    "mount868_3": "8x6x8",
    "mount868_4": "8x6x8",
    "mount868_5": "8x6x8",
    "mount343_1": "3x4x3",
    "mount343_2": "3x4x3",
    "mount343_3": "3x4x3",
    "mount343_4": "3x4x3",
    "mount343_5": "3x4x3",
    "mount343_6": "3x4x3",
    "mount232_1": "2x3x2",
    "mount232_2": "2x3x2",
    "mount346_1": "3x16x6",
    "mount346_2": "3x16x6",
    "mount346_3": "3x16x6",
    "mount346_4": "3x16x6",
    "mount346_5": "3x16x6",
    "mount346_6": "3x16x6",
    "mount346_7": "3x16x6",
    "mount346_8": "3x16x6"
  },
  "compartments": {
    "comp618_1": "6x1x8",
    "comp618_2": "6x1x8",
    "comp618_3": "6x1x8",
    "comp618_4": "6x1x8",
    "comp618_5": "6x1x8",
    "comp618_6": "6x1x8",
    "comp616_1": "6x1x6",
    "comp616_2": "6x1x6",
    "comp616_3": "6x1x6",
    "comp616_4": "6x1x6",
    "comp616_5": "6x1x6",
    "comp616_6": "6x1x6",
    "comp616_7": "6x1x6",
    "comp616_8": "6x1x6",
    "comp616_9": "6x1x6",
    "comp614_1": "4x1x6",
    "comp614_2": "4x1x6"
  },
  "modules": {
    "module101010drive_1": "10x10x10",
    "module101010drive_2": "10x10x10",
    "module666reactor_1": "6x6x6",
    "module666reactor_2": "6x6x6",
    "module666reactor_3": "6x6x6",
    "module333_1": "3x3x3",
    "module333_2": "3x3x3",
    "module333_3": "3x3x3",
    "module333_4": "3x3x3",
    "module333_5": "3x3x3",
    "module333_6": "3x3x3",
    "module333_7": "3x3x3",
    "module222radar_": "2x2x2",
    "module222_1": "2x2x2"
  }
}
